setup.py
DynaMIT.egg-info/PKG-INFO
DynaMIT.egg-info/SOURCES.txt
DynaMIT.egg-info/dependency_links.txt
DynaMIT.egg-info/requires.txt
DynaMIT.egg-info/top_level.txt
dynamit/__init__.py
dynamit/__main__.py
dynamit/alignmentStrategy.py
dynamit/biclusteringStrategy.py
dynamit/bidimensionalSpacePrinter.py
dynamit/clusterEvaluationPrinter.py
dynamit/cmfinderSearcher.py
dynamit/configurationGenerator.py
dynamit/cooccurrenceStrategy.py
dynamit/gibbsSearcher.py
dynamit/glam2Searcher.py
dynamit/graphProtSearcher.py
dynamit/heatmapPrinter.py
dynamit/homerSearcher.py
dynamit/integrationStrategy.py
dynamit/jaccardStrategy.py
dynamit/knownSitesSearcher.py
dynamit/matrixSearcher.py
dynamit/mdScanSearcher.py
dynamit/memeSearcher.py
dynamit/memerisSearcher.py
dynamit/miStrategy.py
dynamit/motifSearcher.py
dynamit/pcaStrategy.py
dynamit/positionalDensityPrinter.py
dynamit/previousResultsLoaderSearcher.py
dynamit/proximityStrategy.py
dynamit/regionsIntersectionSearcher.py
dynamit/resultsPrinter.py
dynamit/rnaForesterSearcher.py
dynamit/rnaHybridSearcher.py
dynamit/rnaProfileSearcher.py
dynamit/runner.py
dynamit/sequenceViewPrinter.py
dynamit/tablePrinter.py
dynamit/utils.py
dynamit/webLogoPrinter.py
dynamit/weederSearcher.py
dynamit/graphics/logo_noname.gif