Metadata-Version: 1.1
Name: DynaMIT
Version: 1.1.3
Summary: the Dynamic Motif Integration Toolkit
Home-page: https://bitbucket.org/erikdassi/dynamit
Author: Erik Dassi
Author-email: erik.dassi@unitn.it
License: UNKNOWN
Platform: UNKNOWN
Classifier: Programming Language :: Python
Classifier: Programming Language :: Python :: 2
Classifier: Programming Language :: Python :: 3
Classifier: License :: OSI Approved :: GNU General Public License v3 or later (GPLv3+)
Classifier: Operating System :: OS Independent
Classifier: Development Status :: 5 - Production/Stable
Classifier: Environment :: Console
Classifier: Intended Audience :: Science/Research
Classifier: Topic :: Scientific/Engineering :: Bio-Informatics
